observo_handler/__init__.py
observo_handler/handler.py
observo_handler/middleware.py
observo_handler-1.0.0.dist-info/licenses/LICENSE
observo_handler-1.0.0.dist-info/METADATA
observo_handler-1.0.0.dist-info/WHEEL
observo_handler-1.0.0.dist-info/top_level.txt
observo_handler-1.0.0.dist-info/RECORD
