Metadata-Version: 2.4
Name: observo-handler
Version: 1.0.0
Summary: Real-time logging handler for Observo platform
Home-page: https://github.com/yourusername/observo-handler
Author: Your Name
Author-email: Your Name <your.email@example.com>
License: MIT
Project-URL: Homepage, https://github.com/yourusername/observo-handler
Project-URL: Documentation, https://github.com/yourusername/observo-handler
Project-URL: Repository, https://github.com/yourusername/observo-handler
Requires-Python: >=3.8
License-File: LICENSE
Requires-Dist: build>=1.2.2.post1
Requires-Dist: requests>=2.25.0
Requires-Dist: setuptools>=75.3.2
Requires-Dist: twine>=6.1.0
Requires-Dist: wheel>=0.45.1
Dynamic: author
Dynamic: home-page
Dynamic: license-file
Dynamic: requires-python
